{
  "id": "x7zgq3r04",
  "type": "analyst",
  "subject": "Analyze collected data, resear",
  "description": "Analyze collected data, research relevant CVEs, and compile security findings report",
  "status": "failed",
  "blocks": [],
  "blockedBy": [],
  "metadata": {
    "taskId": "x7zgq3r04",
    "objective": "Analyze collected data, research relevant CVEs, and compile security findings report",
    "completionCriteria": [
      "CVE mappings",
      "Risk severity ratings",
      " Remediation recommendations",
      "Final audit report"
    ],
    "prohibitedActions": [
      "No exploitation attempts",
      "No unauthorized disclosure"
    ],
    "maxTurns": 6,
    "skill": "analyst",
    "finalOutput": ""
  },
  "createdAt": 1776850537323,
  "updatedAt": 1776850565956,
  "logFile": "D:\\Projects\\Github\\Mibu-101\\.redlock\\tasks\\x7zgq3r04\\output.log",
  "logDir": "D:\\Projects\\Github\\Mibu-101\\.redlock\\tasks\\x7zgq3r04"
}