{
  "id": "x8lxi2ker",
  "type": "analyst",
  "subject": "Analyze findings, research rel",
  "description": "Analyze findings, research relevant CVEs, correlate data, and compile comprehensive security audit report",
  "status": "completed",
  "blocks": [],
  "blockedBy": [],
  "metadata": {
    "taskId": "x8lxi2ker",
    "objective": "Analyze findings, research relevant CVEs, correlate data, and compile comprehensive security audit report",
    "completionCriteria": [
      "Final audit report with severity ratings",
      "CVE references",
      "Remediation recommendations"
    ],
    "prohibitedActions": [
      "No external communications"
    ],
    "maxTurns": 6,
    "skill": "analyst",
    "finalOutput": ""
  },
  "createdAt": 1776850294934,
  "updatedAt": 1776850352960,
  "logFile": "D:\\Projects\\Github\\Mibu-101\\.redlock\\tasks\\x8lxi2ker\\output.log",
  "logDir": "D:\\Projects\\Github\\Mibu-101\\.redlock\\tasks\\x8lxi2ker"
}